lektor_atom.py
lektor_atom_feed-0.5.dist-info/DESCRIPTION.rst
lektor_atom_feed-0.5.dist-info/METADATA
lektor_atom_feed-0.5.dist-info/RECORD
lektor_atom_feed-0.5.dist-info/WHEEL
lektor_atom_feed-0.5.dist-info/entry_points.txt
lektor_atom_feed-0.5.dist-info/metadata.json
lektor_atom_feed-0.5.dist-info/top_level.txt
