Metadata-Version: 2.0
Name: lektor-atom-feed
Version: 0.5
Summary: UNKNOWN
Home-page: https://github.com/VaultVulp/lektor-atom
Author: A. Jesse Jiryu Davis
Author-email: jesse@emptysquare.net
License: MIT
Platform: UNKNOWN
Requires-Dist: MarkupSafe
